gpt_readme_reader/__init__.py
gpt_readme_reader/gpt_readme_reader.py
gpt_readme_reader-0.0.2.dist-info/METADATA
gpt_readme_reader-0.0.2.dist-info/WHEEL
gpt_readme_reader-0.0.2.dist-info/entry_points.txt
gpt_readme_reader-0.0.2.dist-info/top_level.txt
gpt_readme_reader-0.0.2.dist-info/RECORD
