Metadata-Version: 2.1
Name: gpt-readme-reader
Version: 0.0.2
Summary: A utility to extract setup commands from a GitHub repository
Home-page: https://github.com/felvin-search/gpt-readme-reader
Author: Felvin
Author-email: team@felvin.com
License: UNKNOWN
Platform: UNKNOWN
Classifier: Development Status :: 3 - Alpha
Classifier: Intended Audience :: Developers
Classifier: License :: OSI Approved :: MIT License
Classifier: Operating System :: OS Independent
Classifier: Programming Language :: Python :: 3
Classifier: Programming Language :: Python :: 3.6
Classifier: Programming Language :: Python :: 3.7
Classifier: Programming Language :: Python :: 3.8
Classifier: Programming Language :: Python :: 3.9
Requires-Python: >=3.6
Requires-Dist: EbookLib (==0.18)
Requires-Dist: Flask-Cors (==3.0.10)
Requires-Dist: Flask (==2.2.3)
Requires-Dist: GitPython (==3.1.31)
Requires-Dist: Jinja2 (==3.1.2)
Requires-Dist: MarkupSafe (==2.1.2)
Requires-Dist: Pillow (==9.4.0)
Requires-Dist: PyYAML (==6.0)
Requires-Dist: Pygments (==2.14.0)
Requires-Dist: SQLAlchemy (==1.4.46)
Requires-Dist: SecretStorage (==3.3.3)
Requires-Dist: Werkzeug (==2.2.3)
Requires-Dist: aiohttp (==3.8.4)
Requires-Dist: aiosignal (==1.3.1)
Requires-Dist: anyio (==3.6.2)
Requires-Dist: asttokens (==2.2.1)
Requires-Dist: async-timeout (==4.0.2)
Requires-Dist: attrs (==22.2.0)
Requires-Dist: backcall (==0.2.0)
Requires-Dist: beautifulsoup4 (==4.12.0)
Requires-Dist: bleach (==6.0.0)
Requires-Dist: blobfile (==2.0.1)
Requires-Dist: bs4 (==0.0.1)
Requires-Dist: certifi (==2022.12.7)
Requires-Dist: cffi (==1.15.1)
Requires-Dist: charset-normalizer (==3.0.1)
Requires-Dist: chromadb (==0.3.4)
Requires-Dist: click-log (==0.4.0)
Requires-Dist: click (==8.1.3)
Requires-Dist: clickhouse-connect (==0.5.12)
Requires-Dist: colorama (==0.4.6)
Requires-Dist: comm (==0.1.2)
Requires-Dist: cryptography (==39.0.1)
Requires-Dist: dataclasses-json (==0.5.7)
Requires-Dist: debugpy (==1.6.6)
Requires-Dist: decorator (==5.1.1)
Requires-Dist: deprecation (==2.1.0)
Requires-Dist: docutils (==0.19)
Requires-Dist: docx2txt (==0.8)
Requires-Dist: dotty-dict (==1.3.1)
Requires-Dist: duckdb (==0.7.0)
Requires-Dist: executing (==1.2.0)
Requires-Dist: fastapi (==0.92.0)
Requires-Dist: filelock (==3.9.0)
Requires-Dist: frozenlist (==1.3.3)
Requires-Dist: gitdb (==4.0.10)
Requires-Dist: gotrue (==1.0.0)
Requires-Dist: gpt-index (==0.4.8)
Requires-Dist: greenlet (==2.0.2)
Requires-Dist: gunicorn (==20.1.0)
Requires-Dist: h11 (==0.14.0)
Requires-Dist: hnswlib (==0.7.0)
Requires-Dist: httpcore (==0.16.3)
Requires-Dist: httptools (==0.5.0)
Requires-Dist: httpx (==0.23.3)
Requires-Dist: huggingface-hub (==0.12.1)
Requires-Dist: idna (==3.4)
Requires-Dist: importlib-metadata (==6.0.0)
Requires-Dist: importlib-resources (==5.12.0)
Requires-Dist: invoke (==1.7.3)
Requires-Dist: ipykernel (==6.21.2)
Requires-Dist: ipython (==8.10.0)
Requires-Dist: itsdangerous (==2.1.2)
Requires-Dist: jaraco.classes (==3.2.3)
Requires-Dist: jedi (==0.18.2)
Requires-Dist: jeepney (==0.8.0)
Requires-Dist: joblib (==1.2.0)
Requires-Dist: jupyter-client (==8.0.3)
Requires-Dist: jupyter-core (==5.2.0)
Requires-Dist: keyring (==23.13.1)
Requires-Dist: langchain (==0.0.91)
Requires-Dist: lxml (==4.9.2)
Requires-Dist: lz4 (==4.3.2)
Requires-Dist: marshmallow-enum (==1.5.1)
Requires-Dist: marshmallow (==3.19.0)
Requires-Dist: matplotlib-inline (==0.1.6)
Requires-Dist: more-itertools (==9.0.0)
Requires-Dist: multidict (==6.0.4)
Requires-Dist: mypy-extensions (==1.0.0)
Requires-Dist: nest-asyncio (==1.5.6)
Requires-Dist: nltk (==3.8.1)
Requires-Dist: numpy (==1.24.2)
Requires-Dist: nvidia-cublas-cu11 (==11.10.3.66)
Requires-Dist: nvidia-cuda-nvrtc-cu11 (==11.7.99)
Requires-Dist: nvidia-cuda-runtime-cu11 (==11.7.99)
Requires-Dist: nvidia-cudnn-cu11 (==8.5.0.96)
Requires-Dist: openai (==0.26.5)
Requires-Dist: packaging (==23.0)
Requires-Dist: pandas (==1.5.3)
Requires-Dist: parso (==0.8.3)
Requires-Dist: pexpect (==4.8.0)
Requires-Dist: pickleshare (==0.7.5)
Requires-Dist: pkginfo (==1.9.6)
Requires-Dist: platformdirs (==3.0.0)
Requires-Dist: postgrest-py (==0.10.3)
Requires-Dist: prompt-toolkit (==3.0.37)
Requires-Dist: psutil (==5.9.4)
Requires-Dist: ptyprocess (==0.7.0)
Requires-Dist: pure-eval (==0.2.2)
Requires-Dist: pycparser (==2.21)
Requires-Dist: pycryptodomex (==3.17)
Requires-Dist: pydantic (==1.10.5)
Requires-Dist: pypdf2 (==3.0.1)
Requires-Dist: pytesseract (==0.3.10)
Requires-Dist: python-dateutil (==2.8.2)
Requires-Dist: python-docx (==0.8.11)
Requires-Dist: python-dotenv (==0.21.1)
Requires-Dist: python-gitlab (==3.13.0)
Requires-Dist: python-semantic-release (==7.33.0)
Requires-Dist: pytz (==2022.7.1)
Requires-Dist: pyzmq (==25.0.0)
Requires-Dist: readme-renderer (==37.3)
Requires-Dist: realtime (==1.0.0)
Requires-Dist: regex (==2022.10.31)
Requires-Dist: requests-toolbelt (==0.10.1)
Requires-Dist: requests (==2.28.2)
Requires-Dist: rfc3986 (==1.5.0)
Requires-Dist: scikit-learn (==1.2.1)
Requires-Dist: scipy (==1.10.1)
Requires-Dist: semver (==2.13.0)
Requires-Dist: sentence-transformers (==2.2.2)
Requires-Dist: sentencepiece (==0.1.97)
Requires-Dist: six (==1.16.0)
Requires-Dist: smmap (==5.0.0)
Requires-Dist: sniffio (==1.3.0)
Requires-Dist: soupsieve (==2.4)
Requires-Dist: stack-data (==0.6.2)
Requires-Dist: starlette (==0.25.0)
Requires-Dist: storage3 (==0.5.0)
Requires-Dist: supabase (==1.0.0)
Requires-Dist: supafunc (==0.2.2)
Requires-Dist: tenacity (==8.1.0)
Requires-Dist: threadpoolctl (==3.1.0)
Requires-Dist: tiktoken (==0.2.0)
Requires-Dist: tokenizers (==0.13.2)
Requires-Dist: tomlkit (==0.11.6)
Requires-Dist: torch (==1.13.1)
Requires-Dist: torchvision (==0.14.1)
Requires-Dist: tornado (==6.2)
Requires-Dist: tqdm (==4.64.1)
Requires-Dist: traitlets (==5.9.0)
Requires-Dist: transformers (==4.26.1)
Requires-Dist: twine (==3.8.0)
Requires-Dist: typing-extensions (==4.5.0)
Requires-Dist: typing-inspect (==0.8.0)
Requires-Dist: urllib3 (==1.26.14)
Requires-Dist: uvicorn (==0.20.0)
Requires-Dist: uvloop (==0.17.0)
Requires-Dist: watchfiles (==0.18.1)
Requires-Dist: wcwidth (==0.2.6)
Requires-Dist: webencodings (==0.5.1)
Requires-Dist: websockets (==10.4)
Requires-Dist: yarl (==1.8.2)
Requires-Dist: zipp (==3.14.0)
Requires-Dist: zstandard (==0.20.0)
